creditagricole
