Metadata-Version: 2.1
Name: credit-agricole
Version: 0.1.3
Summary: Python library that allows you to retrieve bank details from the Credit Agricole website
Home-page: https://github.com/ShellCode33/Python-Credit-Agricole
Author: ShellCode
Author-email: shellcode33@protonmail.ch
License: MIT
Keywords: credit agricole bank account card loan insurance
Platform: UNKNOWN
Classifier: Programming Language :: Python :: 3.6
Classifier: Programming Language :: Python :: 3.7
Classifier: Programming Language :: Python :: 3.8
Classifier: Programming Language :: Python :: 3.9
Classifier: Programming Language :: Python :: 3.10
Classifier: License :: OSI Approved :: MIT License
Classifier: Operating System :: POSIX :: Linux
Requires-Python: >=3.6
License-File: LICENSE
